colrev/__init__.py
colrev/__version__.py
colrev/constants.py
colrev/dataset.py
colrev/exceptions.py
colrev/logger.py
colrev/paths.py
colrev/py.typed
colrev/readme.md
colrev/review_manager.py
colrev/settings.py
colrev/env/__init__.py
colrev/env/complementary_material_keywords.txt
colrev/env/complementary_material_prefixes.txt
colrev/env/complementary_material_strings.txt
colrev/env/docker_manager.py
colrev/env/environment_manager.py
colrev/env/grobid_service.py
colrev/env/journal_rankings.csv
colrev/env/language_service.py
colrev/env/local_index.py
colrev/env/local_index_builder.py
colrev/env/local_index_prep.py
colrev/env/local_index_sqlite.py
colrev/env/masterdata_curations.csv
colrev/env/resources.py
colrev/env/tei_parser.py
colrev/env/utils.py
colrev/hooks/__init__.py
colrev/hooks/check.py
colrev/hooks/format.py
colrev/hooks/report.py
colrev/hooks/share.py
colrev/linter/colrev_direct_status_assign.py
colrev/linter/colrev_missed_constant_usage.py
colrev/linter/colrev_records_variable_naming_convention.py
colrev/linter/readme.md
colrev/loader/__init__.py
colrev/loader/bib.py
colrev/loader/enl.py
colrev/loader/json.py
colrev/loader/load_utils.py
colrev/loader/load_utils_formatter.py
colrev/loader/load_utils_name_formatter.py
colrev/loader/loader.py
colrev/loader/md.py
colrev/loader/nbib.py
colrev/loader/ris.py
colrev/loader/table.py
colrev/ops/__init__.py
colrev/ops/advisor.py
colrev/ops/check.py
colrev/ops/checker.py
colrev/ops/clone.py
colrev/ops/colrev_pandas.py
colrev/ops/commit.py
colrev/ops/correct.py
colrev/ops/data.py
colrev/ops/dedupe.py
colrev/ops/distribute.py
colrev/ops/init.py
colrev/ops/load.py
colrev/ops/merge.py
colrev/ops/pdf_get.py
colrev/ops/pdf_get_man.py
colrev/ops/pdf_prep.py
colrev/ops/pdf_prep_man.py
colrev/ops/prep.py
colrev/ops/prep_debug.py
colrev/ops/prep_man.py
colrev/ops/prescreen.py
colrev/ops/pull.py
colrev/ops/push.py
colrev/ops/remove.py
colrev/ops/repare.py
colrev/ops/screen.py
colrev/ops/search.py
colrev/ops/search_api_feed.py
colrev-0.14.0.dist-info/METADATA
colrev-0.14.0.dist-info/WHEEL
colrev-0.14.0.dist-info/entry_points.txt
colrev-0.14.0.dist-info/licenses/LICENSE
colrev-0.14.0.dist-info/RECORD
