Metadata-Version: 2.4
Name: colrev
Version: 0.14.0
Summary: CoLRev: An open-source environment for collaborative reviews
Author-email: Gerit Wagner <gerit.wagner@uni-bamberg.de>, Julian Prester <julian.prester@sydney.edu.au>
License: MIT
License-File: LICENSE
Keywords: literature,literature review,open science,reproducible research,research,systematic literature review,systematic review
Classifier: Development Status :: 4 - Beta
Classifier: License :: OSI Approved :: MIT License
Classifier: Natural Language :: English
Classifier: Operating System :: OS Independent
Classifier: Programming Language :: Python :: 3
Classifier: Programming Language :: Python :: 3.8
Classifier: Programming Language :: Python :: 3.9
Classifier: Programming Language :: Python :: 3.10
Classifier: Programming Language :: Python :: 3.11
Classifier: Programming Language :: Python :: 3.12
Classifier: Topic :: Scientific/Engineering
Classifier: Typing :: Typed
Requires-Python: <3.13,>=3.10
Requires-Dist: bib-dedupe>=0.10.0
Requires-Dist: click-repl>=0.3.0
Requires-Dist: click>=8.1.6
Requires-Dist: dictdiffer>=0.9.0
Requires-Dist: docker==7.1.0
Requires-Dist: gitpython>=3.1.29
Requires-Dist: glom>=22.1.0
Requires-Dist: imagehash>=4.3.1
Requires-Dist: inquirer>=3.1.3
Requires-Dist: jinja2>=3.1.2
Requires-Dist: lingua-language-detector>=2.0.2
Requires-Dist: lxml>=5.2.0
Requires-Dist: nameparser>=1.1.2
Requires-Dist: number-parser>=0.3.2
Requires-Dist: openpyxl>=3.1.2
Requires-Dist: pandas>=2.2
Requires-Dist: pre-commit>=3.2.0
Requires-Dist: pycountry>=24.6.1
Requires-Dist: pydantic>=2.9.1
Requires-Dist: pymupdf>=1.24.3
Requires-Dist: pyyaml>=6.0.0
Requires-Dist: rapidfuzz>=3.5.2
Requires-Dist: requests-cache>=0.9.6
Requires-Dist: requests>=2.32.0
Requires-Dist: toml>=0.10.2
Requires-Dist: tqdm>=4.64.1
Provides-Extra: dev
Requires-Dist: coverage-badge>=1.1.0; extra == 'dev'
Requires-Dist: coverage[toml]>=7.3.2; extra == 'dev'
Requires-Dist: mypy==1.12.0; extra == 'dev'
Requires-Dist: pylint==3.0.1; extra == 'dev'
Requires-Dist: pytest-mock>=3.10.0; extra == 'dev'
Requires-Dist: pytest-skip-slow>=0.0.5; extra == 'dev'
Requires-Dist: pytest>=7.2.1; extra == 'dev'
Requires-Dist: requests-mock>=1.10.0; extra == 'dev'
Requires-Dist: types-click>=7.1.8; extra == 'dev'
Provides-Extra: docs
Requires-Dist: beautifulsoup4>=4.11.1; extra == 'docs'
Requires-Dist: docutils!=0.21.post1; extra == 'docs'
Requires-Dist: m2r>=0.3.1; extra == 'docs'
Requires-Dist: sphinx-autodoc-typehints>=1.19.4; extra == 'docs'
Requires-Dist: sphinx-click>=4.3.0; extra == 'docs'
Requires-Dist: sphinx-collapse>=0.1.2; extra == 'docs'
Requires-Dist: sphinx-copybutton>=0.5.2; extra == 'docs'
Requires-Dist: sphinx-design>=0.5.0; extra == 'docs'
Requires-Dist: sphinx-rtd-theme>=1.1.1; extra == 'docs'
Requires-Dist: sphinx>=5.2.3; extra == 'docs'
Requires-Dist: sphinxcontrib-datatemplates>=0.9.2; extra == 'docs'
